rs_calculator/__init__.py
rs_calculator-0.2.2.dist-info/licenses/LICENSE
rs_calculator-0.2.2.dist-info/METADATA
rs_calculator-0.2.2.dist-info/WHEEL
rs_calculator-0.2.2.dist-info/top_level.txt
rs_calculator-0.2.2.dist-info/RECORD
