Metadata-Version: 2.4
Name: rs_calculator
Version: 0.2.2
Summary: A simple calculator library for Python beginners
Home-page: https://github.com/Rasa8877/rs-calculator
Author: Rasa Dariush
Author-email: Rasa Dariush <letperhut@gmail.com>
License: MIT
Project-URL: Homepage, https://github.com/Rasa8877/rs-calculator
Classifier: Programming Language :: Python :: 3
Classifier: License :: OSI Approved :: MIT License
Classifier: Intended Audience :: Education
Classifier: Operating System :: OS Independent
Requires-Python: >=3.6
License-File: LICENSE
Requires-Dist: asteval>=0.9.26
Dynamic: author
Dynamic: home-page
Dynamic: license-file
Dynamic: requires-python
